dateling/__init__.py
dateling/resolver.py
dateling-1.3.2.dist-info/licenses/LICENSE
dateling-1.3.2.dist-info/METADATA
dateling-1.3.2.dist-info/WHEEL
dateling-1.3.2.dist-info/top_level.txt
dateling-1.3.2.dist-info/RECORD
