Metadata-Version: 2.4
Name: dateling
Version: 1.3.2
Summary: dateling provides a normalized formal language and grammar for handling relative time expressions. It includes a DSL (domain-specific language) to represent time anchors, offsets, and modifiers, along with a robust parser and resolver to evaluate these expressions into concrete dates. The name 'dateling' comes from combining 'date' and 'handling', reflecting its purpose of handling complex date computations
Home-page: https://github.com/nostaljic/dateling
Author: jaypyon
Author-email: scorpion@dgu.ac.kr
Requires-Python: >=3.11
License-File: LICENSE
Requires-Dist: pandas
Requires-Dist: python-dateutil
Dynamic: author
Dynamic: author-email
Dynamic: description
Dynamic: description-content-type
Dynamic: home-page
Dynamic: license-file
Dynamic: requires-dist
Dynamic: requires-python
Dynamic: summary
